<annotation>
	<folder>face</folder>
	<filename>952.jpg</filename>
	<path>/home/sinjab/Desktop/labelImg/data/face/952.jpg</path>
	<source>
		<database>Unknown</database>
	</source>
	<size>
		<width>332</width>
		<height>500</height>
		<depth>1</depth>
	</size>
	<segmented>0</segmented>
	<object>
		<name>face</name>
		<pose>Unspecified</pose>
		<truncated>0</truncated>
		<difficult>0</difficult>
		<bndbox>
			<xmin>105</xmin>
			<ymin>42</ymin>
			<xmax>227</xmax>
			<ymax>211</ymax>
		</bndbox>
	</object>
</annotation>
